MANIFEST.in
README.rst
setup.py
src/AUTHORS.txt
src/HISTORY.txt
src/README.txt
src/sphinxjp/__init__.py
src/sphinxjp.themes.tinkerdahlia.egg-info/PKG-INFO
src/sphinxjp.themes.tinkerdahlia.egg-info/SOURCES.txt
src/sphinxjp.themes.tinkerdahlia.egg-info/dependency_links.txt
src/sphinxjp.themes.tinkerdahlia.egg-info/entry_points.txt
src/sphinxjp.themes.tinkerdahlia.egg-info/namespace_packages.txt
src/sphinxjp.themes.tinkerdahlia.egg-info/not-zip-safe
src/sphinxjp.themes.tinkerdahlia.egg-info/requires.txt
src/sphinxjp.themes.tinkerdahlia.egg-info/top_level.txt
src/sphinxjp/themes/__init__.py
src/sphinxjp/themes/tinkerdahlia/__init__.py
src/sphinxjp/themes/tinkerdahlia/templates/tinkerdahlia/layout.html
src/sphinxjp/themes/tinkerdahlia/templates/tinkerdahlia/theme.conf
src/sphinxjp/themes/tinkerdahlia/templates/tinkerdahlia/static/pygments.css
src/sphinxjp/themes/tinkerdahlia/templates/tinkerdahlia/static/tinkerdahlia.css_t